vmp/__init__.py
vmp/vmp.py
vmp-0.0.13.dist-info/METADATA
vmp-0.0.13.dist-info/WHEEL
vmp-0.0.13.dist-info/top_level.txt
vmp-0.0.13.dist-info/RECORD
