Metadata-Version: 2.1
Name: vmp
Version: 0.0.13
Summary: Generating Vocabulary Management Profiles in Python
Home-page: https://github.com/matthewdurward/vmp
Author: Matthew Durward, Christopher Thomson
Author-email: matthew.durward@pg.canterbury.ac.nz
License: GNU GENERAL PUBLIC LICENSE v3
Keywords: text analytics,natural language processing,computational linguistics,vocabulary,lexical diversity,corpus,corpora
Requires-Dist: pandas
Requires-Dist: tqdm
Requires-Dist: clean-text
Requires-Dist: regex
Requires-Dist: requests
Provides-Extra: dev
Requires-Dist: pytest >=7.0 ; extra == 'dev'
Requires-Dist: twine >=4.0.2 ; extra == 'dev'
